eth2fastspec.py
eth2fastspec-0.0.5.dist-info/LICENSE
eth2fastspec-0.0.5.dist-info/METADATA
eth2fastspec-0.0.5.dist-info/WHEEL
eth2fastspec-0.0.5.dist-info/top_level.txt
eth2fastspec-0.0.5.dist-info/RECORD
