Metadata-Version: 2.1
Name: eth2fastspec
Version: 0.0.5
Summary: Optimized version of eth2spec
Home-page: https://github.com/protolambda/eth2fastspec
Author: protolambda
Author-email: proto+pip@protolambda.com
License: MIT
Keywords: eth2,pyspec,eth2spec
Platform: UNKNOWN
Classifier: Development Status :: 4 - Beta
Classifier: Intended Audience :: Developers
Classifier: License :: OSI Approved :: MIT License
Classifier: Natural Language :: English
Classifier: Programming Language :: Python :: 3
Classifier: Programming Language :: Python :: 3.8
Classifier: Programming Language :: Python :: Implementation :: PyPy
Classifier: Operating System :: OS Independent
Requires-Python: >=3.8, <4
Requires-Dist: eth2spec (<0.13,>=0.12.1)
Requires-Dist: remerkleable (>=0.1.16)
Requires-Dist: milagro-bls-binding (==1.3.0)
